django_tink_fields-0.3.2.dist-info/licenses/AUTHORS.md
django_tink_fields-0.3.2.dist-info/licenses/LICENSE.txt
tink_fields/__init__.py
tink_fields/fields.py
tink_fields/test/__init__.py
tink_fields/test/models.py
tink_fields/test/test_coverage.py
tink_fields/test/test_fields.py
tink_fields/test/test_new_features.py
tink_fields/test/settings/__init__.py
tink_fields/test/settings/base.py
tink_fields/test/settings/sqlite.py
django_tink_fields-0.3.2.dist-info/METADATA
django_tink_fields-0.3.2.dist-info/WHEEL
django_tink_fields-0.3.2.dist-info/top_level.txt
django_tink_fields-0.3.2.dist-info/RECORD
