Metadata-Version: 2.4
Name: django-tink-fields
Version: 0.3.2
Summary: Tink-based encrypted model fields for Django
Author-email: Isaac Elbaz <script3r@gmail.com>
License: BSD
Project-URL: Homepage, https://github.com/script3r/django-tink-fields/
Project-URL: Repository, https://github.com/script3r/django-tink-fields/
Project-URL: Issues, https://github.com/script3r/django-tink-fields/issues
Classifier: Environment :: Web Environment
Classifier: Intended Audience :: Developers
Classifier: License :: OSI Approved :: BSD License
Classifier: Operating System :: OS Independent
Classifier: Programming Language :: Python
Classifier: Programming Language :: Python :: 3.12
Classifier: Programming Language :: Python :: 3.13
Classifier: Programming Language :: Python :: Implementation :: CPython
Classifier: Programming Language :: Python :: Implementation :: PyPy
Classifier: Framework :: Django
Requires-Python: >=3.12
License-File: LICENSE.txt
License-File: AUTHORS.md
Requires-Dist: Django>=6.0
Requires-Dist: tink>=1.13.0
Requires-Dist: protobuf>=6.33.2
Provides-Extra: dev
Requires-Dist: pytest>=9.0.2; extra == "dev"
Requires-Dist: pytest-django>=4.11.1; extra == "dev"
Requires-Dist: pytest-cov>=7.0.0; extra == "dev"
Requires-Dist: coverage>=7.13.0; extra == "dev"
Requires-Dist: black>=25.12.0; extra == "dev"
Requires-Dist: isort>=7.0.0; extra == "dev"
Requires-Dist: flake8>=7.3.0; extra == "dev"
Requires-Dist: pyright>=1.1.407; extra == "dev"
Requires-Dist: sphinx<9,>=8.2.0; extra == "dev"
Requires-Dist: sphinx-rtd-theme>=3.0.2; extra == "dev"
Provides-Extra: test
Requires-Dist: pytest>=9.0.2; extra == "test"
Requires-Dist: pytest-django>=4.11.1; extra == "test"
Requires-Dist: pytest-cov>=7.0.0; extra == "test"
Requires-Dist: coverage>=7.13.0; extra == "test"
Requires-Dist: factory-boy>=3.3.3; extra == "test"
Requires-Dist: freezegun>=1.5.5; extra == "test"
Dynamic: license-file
